{
  "users": [
    {
      "id": "1",
      "username": "user1",
      "password": "123456"
    },
    {
      "id": "2",
      "username": "user2",
      "password": "password2"
    }
  ],
  "items": [
    {
      "id": "678",
      "name": "Pedido de Compra:",
      "description": "realizado na data 11/08/2023"
    },
    {
      "id": "795",
      "name": "⁠Pedido no estoque:",
      "description": "realizado na data 12/04/2024"
    },
    {
      "id": "827",
      "name": "Pedido de entrega:",
      "description": "realizado na data 12/07/2022"
    }
  ]
}